extism_sys-1.12.0.dist-info/METADATA
extism_sys-1.12.0.dist-info/WHEEL
extism_sys/__init__.py
extism_sys/ffi.py
extism_sys/libextism_sys.so
extism_sys-1.12.0.dist-info/RECORD
