Metadata-Version: 2.4
Name: extism-sys
Version: 1.12.0
Classifier: Programming Language :: Rust
Classifier: Programming Language :: Python :: Implementation :: CPython
Classifier: Programming Language :: Python :: Implementation :: PyPy
Requires-Dist: cffi
Home-Page: https://extism.org
License: BSD-3-Clause
Requires-Python: >=3.7
Project-URL: Source Code, https://github.com/extism/extism
